examples/__init__.py
examples/examples.py
examples/sensor.py
pi_sht1x/__init__.py
pi_sht1x/logging.py
pi_sht1x/sht1x.py
pi_sht1x-1.0.10.dist-info/AUTHORS
pi_sht1x-1.0.10.dist-info/LICENSE
pi_sht1x-1.0.10.dist-info/METADATA
pi_sht1x-1.0.10.dist-info/WHEEL
pi_sht1x-1.0.10.dist-info/top_level.txt
pi_sht1x-1.0.10.dist-info/RECORD
