Metadata-Version: 2.1
Name: pi-sht1x
Version: 1.0.10
Summary: Python 3 library for Sensirion SHT1x series of temperature & humidity sensors for the Raspberry Pi.
Home-page: https://github.com/drohm/pi-sht1x
Author: Doug Rohm
Author-email: pypi@dougrohm.com
License: MIT
Download-URL: https://github.com/drohm/pi-sht1x/releases/tag/1.0.10
Keywords: sht sensor sht1x sensirion T temperature humidity RH dew-point celsius measurement gpio serial 2-wire crc crc-8 hardware driver ic
Platform: UNKNOWN
Classifier: Development Status :: 5 - Production/Stable
Classifier: Environment :: Console
Classifier: Intended Audience :: Developers
Classifier: Intended Audience :: End Users/Desktop
Classifier: Intended Audience :: Manufacturing
Classifier: Intended Audience :: Science/Research
Classifier: Intended Audience :: System Administrators
Classifier: License :: OSI Approved :: MIT License
Classifier: Operating System :: POSIX :: Linux
Classifier: Programming Language :: Python :: 3.4
Classifier: Programming Language :: Python :: 3 :: Only
Classifier: Topic :: Home Automation
Classifier: Topic :: Scientific/Engineering :: Atmospheric Science
Classifier: Topic :: System :: Hardware :: Hardware Drivers
Classifier: Topic :: System :: Monitoring
Classifier: Topic :: System :: Operating System Kernels :: Linux
Classifier: Topic :: Software Development
Classifier: Topic :: Utilities
License-File: LICENSE
License-File: AUTHORS
Requires-Dist: RPi.GPIO (>=0.7.0)
